django_navtag/__init__.py
django_navtag/models.py
django_navtag/templatetags/__init__.py
django_navtag/templatetags/navtag.py
django_navtag-3.3.1.dist-info/licenses/LICENSE
django_navtag-3.3.1.dist-info/METADATA
django_navtag-3.3.1.dist-info/WHEEL
django_navtag-3.3.1.dist-info/top_level.txt
django_navtag-3.3.1.dist-info/RECORD
