Metadata-Version: 2.4
Name: django-navtag
Version: 3.3.1
Summary: A simple Django navigation template tag
Author-email: Chris Beaven <smileychris@gmail.com>
License-Expression: MIT
Project-URL: Homepage, https://github.com/SmileyChris/django-navtag
Keywords: django,templates
Classifier: Development Status :: 5 - Production/Stable
Classifier: Environment :: Web Environment
Classifier: Intended Audience :: Developers
Classifier: Operating System :: OS Independent
Classifier: Programming Language :: Python
Classifier: Programming Language :: Python :: 3 :: Only
Classifier: Programming Language :: Python :: 3.9
Classifier: Programming Language :: Python :: 3.10
Classifier: Programming Language :: Python :: 3.11
Classifier: Programming Language :: Python :: 3.12
Classifier: Framework :: Django
Classifier: Framework :: Django :: 3.2
Classifier: Framework :: Django :: 4.2
Classifier: Framework :: Django :: 5.0
Classifier: Framework :: Django :: 5.1
Requires-Python: >=3.9
License-File: LICENSE
Dynamic: license-file
